skrf/__init__.py
skrf/circuit.py
skrf/constants.py
skrf/frequency.py
skrf/instances.py
skrf/mathFunctions.py
skrf/network.py
skrf/networkSet.py
skrf/plotting.py
skrf/qfactor.py
skrf/taper.py
skrf/time.py
skrf/tlineFunctions.py
skrf/util.py
skrf/vectorFitting.py
skrf/calibration/__init__.py
skrf/calibration/calibration.py
skrf/calibration/calibrationSet.py
skrf/calibration/deembedding.py
skrf/calibration/tests/test_calibration.py
skrf/calibration/tests/test_calibrationSet.py
skrf/calibration/tests/test_deembedding.py
skrf/data/__init__.py
skrf/data/delay_short.s1p
skrf/data/ieeetrans.mplstyle
skrf/data/ind.s2p
skrf/data/line.s2p
skrf/data/ntwk1.s2p
skrf/data/one_port.cal
skrf/data/open.s2p
skrf/data/ring slot measured.s1p
skrf/data/ring slot.s2p
"skrf/data/ro,1.s1p"
"skrf/data/ro,2.s1p"
"skrf/data/ro,3.s1p"
skrf/data/short.s1p
skrf/data/short.s2p
skrf/data/skrf.mplstyle
skrf/data/skrf2.mplstyle
skrf/data/skrf2_wide.mplstyle
skrf/data/skrf_wide.mplstyle
skrf/data/tee.s3p
"skrf/data/wr1p5,line.s2p"
"skrf/data/wr1p5,short.s1p"
"skrf/data/wr2p2,delayshort.s1p"
"skrf/data/wr2p2,line.s2p"
"skrf/data/wr2p2,line1.s2p"
"skrf/data/wr2p2,short.s1p"
skrf/io/__init__.py
skrf/io/citi.py
skrf/io/csv.py
skrf/io/general.py
skrf/io/mdif.py
skrf/io/metas.py
skrf/io/touchstone.py
skrf/io/tests/test_citi.py
skrf/io/tests/test_csv.py
skrf/io/tests/test_io.py
skrf/io/tests/test_mdif.py
skrf/io/tests/test_touchstone.py
skrf/io/tests/test_ts_spec.py
skrf/media/__init__.py
skrf/media/circularWaveguide.py
skrf/media/coaxial.py
skrf/media/cpw.py
skrf/media/definedAEpTandZ0.py
skrf/media/device.py
skrf/media/distributedCircuit.py
skrf/media/freespace.py
skrf/media/media.py
skrf/media/mline.py
skrf/media/rectangularWaveguide.py
skrf/media/tests/test_all_construction.py
skrf/media/tests/test_coaxial.py
skrf/media/tests/test_cpw.py
skrf/media/tests/test_definedaeptandz0.py
skrf/media/tests/test_distributedCircuit.py
skrf/media/tests/test_media.py
skrf/media/tests/test_mline.py
scikit_rf-1.10.0.dist-info/METADATA
scikit_rf-1.10.0.dist-info/WHEEL
scikit_rf-1.10.0.dist-info/top_level.txt
scikit_rf-1.10.0.dist-info/RECORD
